danegovpl/__init__.py
danegovpl/__main__.py
danegovpl/api.py
danegovpl/args.py
danegovpl/cli.py
danegovpl/exceptions.py
danegovpl-0.0.2.dist-info/licenses/LICENSE
danegovpl-0.0.2.dist-info/METADATA
danegovpl-0.0.2.dist-info/WHEEL
danegovpl-0.0.2.dist-info/entry_points.txt
danegovpl-0.0.2.dist-info/top_level.txt
danegovpl-0.0.2.dist-info/RECORD
