Metadata-Version: 2.4
Name: danegovpl
Version: 0.0.2
Summary: Api for getting data from dane.gov.pl
Author-email: Dominik Stanisław Suchora <hexderm@gmail.com>
License: GPLv3
Project-URL: Homepage, https://github.com/TUVIMEN/danegovpl
Keywords: api,dane.gov.pl,cli
Classifier: Development Status :: 5 - Production/Stable
Classifier: License :: OSI Approved :: GNU General Public License v3 (GPLv3)
Classifier: Operating System :: OS Independent
Classifier: Programming Language :: Python :: 3
Classifier: Programming Language :: Python :: 3.8
Classifier: Programming Language :: Python :: 3.9
Classifier: Programming Language :: Python :: 3.10
Classifier: Programming Language :: Python :: 3.11
Classifier: Programming Language :: Python :: 3.12
Classifier: Programming Language :: Python :: 3.13
Classifier: Programming Language :: Python :: 3 :: Only
Requires-Python: >=3.8
License-File: LICENSE
Requires-Dist: requests
Requires-Dist: treerequests
Provides-Extra: compression
Requires-Dist: zstandard; extra == "compression"
Dynamic: license-file
